{
  "generator-jhipster": {
    "promptValues": {
      "packageName": "com.masterteknoloji.printarchiver",
      "nativeLanguage": "en"
    },
    "jhipsterVersion": "4.13.0",
    "baseName": "printarchiver",
    "packageName": "com.masterteknoloji.printarchiver",
    "packageFolder": "com/masterteknoloji/printarchiver",
    "serverPort": "8080",
    "authenticationType": "jwt",
    "hibernateCache": "ehcache",
    "clusteredHttpSession": false,
    "websocket": false,
    "databaseType": "sql",
    "devDatabaseType": "mysql",
    "prodDatabaseType": "mysql",
    "searchEngine": false,
    "messageBroker": false,
    "serviceDiscoveryType": false,
    "buildTool": "maven",
    "enableSocialSignIn": false,
    "enableSwaggerCodegen": false,
    "jwtSecretKey": "f8b4c8f4bd996b694efa8ad229f4d728d4322acc",
    "clientFramework": "angular1",
    "useSass": false,
    "clientPackageManager": "npm",
    "applicationType": "monolith",
    "testFrameworks": [],
    "jhiPrefix": "jhi",
    "enableTranslation": true,
    "nativeLanguage": "en",
    "languages": [
      "en",
      "tr"
    ]
  }
}